README.md
phylodeep_data_bdss/__init__.py
phylodeep_data_bdss/large/CNN_FULL_TREE.csv.xz
phylodeep_data_bdss/large/FFNN_SUMSTATS.csv.xz
phylodeep_data_bdss/large/target.csv.xz
phylodeep_data_bdss-0.4.dist-info/LICENSE
phylodeep_data_bdss-0.4.dist-info/METADATA
phylodeep_data_bdss-0.4.dist-info/WHEEL
phylodeep_data_bdss-0.4.dist-info/entry_points.txt
phylodeep_data_bdss-0.4.dist-info/top_level.txt
phylodeep_data_bdss-0.4.dist-info/RECORD
